rowdump/__init__.py
rowdump/core.py
rowdump-0.1.0.dist-info/METADATA
rowdump-0.1.0.dist-info/WHEEL
rowdump-0.1.0.dist-info/licenses/LICENSE
rowdump-0.1.0.dist-info/RECORD
