Metadata-Version: 2.4
Name: rowdump
Version: 0.1.0
Summary: A modern structured Python library for formatted table output
Project-URL: Homepage, https://github.com/markjen/rowdump
Project-URL: Repository, https://github.com/markjen/rowdump
Project-URL: Issues, https://github.com/markjen/rowdump/issues
Author-email: Mark Jen <markjen@gmail.com>
License-Expression: MIT
License-File: LICENSE
Keywords: console,formatting,output,table
Classifier: Development Status :: 4 - Beta
Classifier: Intended Audience :: Developers
Classifier: License :: OSI Approved :: MIT License
Classifier: Programming Language :: Python :: 3
Classifier: Programming Language :: Python :: 3.10
Classifier: Programming Language :: Python :: 3.11
Classifier: Programming Language :: Python :: 3.12
Classifier: Programming Language :: Python :: 3.13
Classifier: Topic :: Software Development :: Libraries :: Python Modules
Classifier: Topic :: Text Processing
Classifier: Topic :: Utilities
Requires-Python: >=3.10
Provides-Extra: dev
Requires-Dist: black>=22.0.0; extra == 'dev'
Requires-Dist: isort>=5.0.0; extra == 'dev'
Requires-Dist: pyright>=1.1.0; extra == 'dev'
Requires-Dist: pytest>=7.0.0; extra == 'dev'
Requires-Dist: ruff>=0.1.0; extra == 'dev'
Provides-Extra: test
Requires-Dist: pytest-cov>=4.0.0; extra == 'test'
Requires-Dist: pytest>=7.0.0; extra == 'test'
